README.rst
setup.py
AiDragonfly/Get_Mesh_Devices_Message.py
AiDragonfly/__init__.py
AiDragonfly/aiqi_bluetooth_device_type.py
AiDragonfly/aiqi_bluetooth_save_json.py
AiDragonfly/aiqi_main.py
AiDragonfly.egg-info/PKG-INFO
AiDragonfly.egg-info/SOURCES.txt
AiDragonfly.egg-info/dependency_links.txt
AiDragonfly.egg-info/requires.txt
AiDragonfly.egg-info/top_level.txt
AiDragonfly/aiqi_model/__init__.py
AiDragonfly/aiqi_model/ble_cc/__init__.py
AiDragonfly/aiqi_model/ble_cc/constantModule.py
AiDragonfly/aiqi_model/ble_cc/motorModule.py
AiDragonfly/aiqi_model/ble_cc/musicModule.py
AiDragonfly/aiqi_model/ble_cc/sensorModule.py
AiDragonfly/aiqi_model/bluetooth/__init__.py
AiDragonfly/aiqi_model/bluetooth/aiqi_bluetooth.py
AiDragonfly/aiqi_model/bluetooth/aiqi_bluetooth_bleak.py
AiDragonfly/aiqi_model/bluetooth/aiqi_bluetooth_uuid.py
AiDragonfly/aiqi_model/mesh/__init__.py
AiDragonfly/aiqi_model/mesh/meshModule.py
AiDragonfly/comm_protocol/__init__.py
AiDragonfly/comm_protocol/aiqi_blue_report.py
AiDragonfly/comm_protocol/aiqi_mesh_report.py
AiDragonfly/common/__init__.py
AiDragonfly/common/onebot_common_function.py